idf2table/__init__.py
idf2table/cli.py
idf2table/core.py
idf2table/obj_export.py
idf2table-0.1.11.dist-info/METADATA
idf2table-0.1.11.dist-info/WHEEL
idf2table-0.1.11.dist-info/entry_points.txt
idf2table-0.1.11.dist-info/RECORD
