Metadata-Version: 2.4
Name: idf2table
Version: 0.1.11
Summary: Convertir des fichiers EnergyPlus IDF en DataFrames pandas
Project-URL: Homepage, https://gitlab.plateforme-tipee.com/idf/idf2table
Project-URL: Documentation, https://gitlab.plateforme-tipee.com/idf/idf2table/-/blob/main/README.md
Project-URL: Repository, https://gitlab.plateforme-tipee.com/idf/idf2table.git
Project-URL: Issues, https://gitlab.plateforme-tipee.com/idf/idf2table/-/issues
Author-email: TIPEE <contact@plateforme-tipee.com>
License: MIT
Keywords: building,dataframe,energyplus,eppy,idf,pandas,simulation
Classifier: Development Status :: 4 - Beta
Classifier: Intended Audience :: Developers
Classifier: Intended Audience :: Science/Research
Classifier: License :: OSI Approved :: MIT License
Classifier: Programming Language :: Python :: 3
Classifier: Programming Language :: Python :: 3.12
Classifier: Programming Language :: Python :: 3.13
Classifier: Topic :: Scientific/Engineering
Classifier: Topic :: Software Development :: Libraries :: Python Modules
Requires-Python: >=3.12
Requires-Dist: openpyxl>=3.1.5
Requires-Dist: pandas>=2.3.3
